pyfineflow/__init__.py
pyfineflow/__main__.py
pyfineflow/core.py
pyfineflow/log_conf.py
pyfineflow/main.py
pyfineflow/schemas.py
pyfineflow/utils.py
pyfineflow-1.1.3.dist-info/LICENSE
pyfineflow-1.1.3.dist-info/METADATA
pyfineflow-1.1.3.dist-info/WHEEL
pyfineflow-1.1.3.dist-info/entry_points.txt
pyfineflow-1.1.3.dist-info/top_level.txt
pyfineflow-1.1.3.dist-info/RECORD
