Metadata-Version: 2.1
Name: pyfineflow
Version: 1.1.3
Summary: python nodes server for fineflow
License-File: LICENSE
Requires-Dist: fastapi[all] (~=0.110.1)
